edc_identifier/__init__.py
edc_identifier/admin.py
edc_identifier/admin_site.py
edc_identifier/apps.py
edc_identifier/checkdigit_mixins.py
edc_identifier/exceptions.py
edc_identifier/identifier.py
edc_identifier/managers.py
edc_identifier/model_mixins.py
edc_identifier/models.py
edc_identifier/offline_models.py
edc_identifier/research_identifier.py
edc_identifier/short_identifier.py
edc_identifier/simple_identifier.py
edc_identifier/subject_identifier.py
edc_identifier/urls.py
edc_identifier/utils.py
edc_identifier/views.py
edc_identifier/migrations/0001_initial.py
edc_identifier/migrations/0001_squashed_0018_auto_20180128_1054.py
edc_identifier/migrations/0002_auto_20160505_1435.py
edc_identifier/migrations/0002_auto_20190305_0123.py
edc_identifier/migrations/0003_auto_20160625_0938.py
edc_identifier/migrations/0003_auto_20191024_1000.py
edc_identifier/migrations/0004_auto_20160807_1443.py
edc_identifier/migrations/0004_auto_20200513_0042.py
edc_identifier/migrations/0005_alter_identifiermodel_managers.py
edc_identifier/migrations/0005_historicalidentifierhistory_historicalidentifiertracker_historicalsubjectidentifier.py
edc_identifier/migrations/0006_alter_identifiermodel_options.py
edc_identifier/migrations/0006_auto_20161127_2226.py
edc_identifier/migrations/0007_alter_identifiermodel_device_created_and_more.py
edc_identifier/migrations/0007_auto_20161204_2227.py
edc_identifier/migrations/0008_alter_identifiermodel_options_and_more.py
edc_identifier/migrations/0008_identifiermodel_linked_identifier.py
edc_identifier/migrations/0009_alter_identifiermodel_site.py
edc_identifier/migrations/0009_auto_20161221_2323.py
edc_identifier/migrations/0010_auto_20170112_0602.py
edc_identifier/migrations/0011_auto_20170511_1323.py
edc_identifier/migrations/0012_auto_20171116_1606.py
edc_identifier/migrations/0013_auto_20171230_1316.py
edc_identifier/migrations/0014_auto_20180103_1322.py
edc_identifier/migrations/0015_auto_20180116_1235.py
edc_identifier-1.0.0.dist-info/AUTHORS
edc_identifier-1.0.0.dist-info/LICENSE
edc_identifier-1.0.0.dist-info/METADATA
edc_identifier-1.0.0.dist-info/WHEEL
edc_identifier-1.0.0.dist-info/top_level.txt
edc_identifier-1.0.0.dist-info/RECORD
